matematikauzbek/__init__.py
matematikauzbek-0.0.1.dist-info/METADATA
matematikauzbek-0.0.1.dist-info/WHEEL
matematikauzbek-0.0.1.dist-info/top_level.txt
matematikauzbek-0.0.1.dist-info/RECORD
