Metadata-Version: 2.1
Name: matematikauzbek
Version: 0.0.1
Summary: Bu kutubxona matematik amal uchun ishlatiladi!
Author: Islombek Hikmatullayev
Author-email: gimlerpro8899@gmail.com
